[
  {
    "text": "Fale conosco",
    "url": "/institucional/fale-conosco"
  },
  {
    "text": "Perguntas Frequentes",
    "url": "/institucional/perguntas-frequentes"
  },
  {
    "text": "Quem somos",
    "url": "/institucional/quem-somos"
  },
  {
    "text": "Formas de Pagamento",
    "url": "/institucional/formas-de-pagamento"
  },
  {
    "text": "Termos de Uso",
    "url": "/institucional/termos-de-uso"
  },
  {
    "text": "Segurança e Privacidade",
    "url": "/institucional/seguranca-e-privacidade"
  }
]
